<?xml version="1.0" ?>
<annotation>
<folder>output-images3</folder>
<filename>air-hole4(hollow-bead)-193.jpg</filename>
<path>E:\Yangdingming\Documents\output-images3\air-hole4(hollow-bead)-193.jpg</path>
<source>
    <database>Unknown</database>
</source>
<size>
    <width>1182</width>
    <height>820</height>
    <depth>3</depth>
</size>

<segmented>0</segmented>
    <object>
    <name>hollow-bead</name>
    <pose>Unspecified</pose>
    <truncated>0</truncated>
    <difficult>0</difficult>
    <bndbox>
        <xmin>211</xmin>
        <ymin>142</ymin>
        <xmax>267</xmax>
        <ymax>190</ymax>
    </bndbox>
</object>
    <object>
    <name>air-hole</name>
    <pose>Unspecified</pose>
    <truncated>0</truncated>
    <difficult>0</difficult>
    <bndbox>
        <xmin>274</xmin>
        <ymin>202</ymin>
        <xmax>296</xmax>
        <ymax>220</ymax>
    </bndbox>
</object>
    <object>
    <name>air-hole</name>
    <pose>Unspecified</pose>
    <truncated>0</truncated>
    <difficult>0</difficult>
    <bndbox>
        <xmin>596</xmin>
        <ymin>495</ymin>
        <xmax>617</xmax>
        <ymax>513</ymax>
    </bndbox>
</object>
    <object>
    <name>air-hole</name>
    <pose>Unspecified</pose>
    <truncated>0</truncated>
    <difficult>0</difficult>
    <bndbox>
        <xmin>901</xmin>
        <ymin>773</ymin>
        <xmax>919</xmax>
        <ymax>787</ymax>
    </bndbox>
</object>
</annotation>
