<?xml version="1.0" ?>
<annotation>
<folder>output-images3</folder>
<filename>unfused4-29.jpg</filename>
<path>E:\Yangdingming\Documents\output-images3\unfused4-29.jpg</path>
<source>
    <database>Unknown</database>
</source>
<size>
    <width>1182</width>
    <height>817</height>
    <depth>3</depth>
</size>

<segmented>0</segmented>
    <object>
    <name>unfused</name>
    <pose>Unspecified</pose>
    <truncated>0</truncated>
    <difficult>0</difficult>
    <bndbox>
        <xmin>336</xmin>
        <ymin>166</ymin>
        <xmax>606</xmax>
        <ymax>396</ymax>
    </bndbox>
</object>
</annotation>
